rrdata/TODO.md
rrdata/__init__.py
rrdata/common/__init__.py
rrdata/common/engine_pgsql.py
rrdata/common/get_update_tradedate.py
rrdata/common/optimiz_df_sql_tmpfile.py
rrdata/common/read_data_from_table.py
rrdata/common/read_df_from_table.py
rrdata/common/save_df_to_pgsql.py
rrdata/common/tusharepro.py
rrdata/common/updtae_sqltable_from_df.py
rrdata/rrdata_init.py
rrdata/rrdatac/__init__.py
rrdata/rrdatac/index/__init__.py
rrdata/rrdatac/index/get_index_sw.py
rrdata/rrdatac/index/read_index_sw.py
rrdata/rrdatac/indicator_tech/README.md
rrdata/rrdatac/indicator_tech/__init__.py
rrdata/rrdatac/indicator_tech/indicator_secs.py
rrdata/rrdatac/rrdataD_read_api.py
rrdata/rrdatac/stock/__init__.py
rrdata/rrdatac/stock/get_stock_adjfactor.py
rrdata/rrdatac/stock/stock_RS_OH_MA.py
rrdata/rrdatad/README.md
rrdata/rrdatad/__init__.py
rrdata/rrdatad/index/__init__.py
rrdata/rrdatad/index/fetch_stock_swclass.sh
rrdata/rrdatad/index/fetch_sw_index_class.py
rrdata/rrdatad/index/fetch_sw_index_cons.py
rrdata/rrdatad/index/fetch_sw_index_daily.py
rrdata/rrdatad/index/fetch_swl_index_spot.py
rrdata/rrdatad/index/fetch_swsindex_stock_class_all.py
rrdata/rrdatad/index/save_index_sw_pgsql.py
rrdata/rrdatad/index/stock_swindex_class_all.csv
rrdata/rrdatad/index/swsindex/StockClassifyUse_stock.xls
rrdata/rrdatad/index/swsindex/SwClass.rar
rrdata/rrdatad/index/swsindex/SwClassCode_2021.xlsx
rrdata/rrdatad/index/swsindex/SwClassStd2021.pdf
rrdata/rrdatad/index/swsindex/stock_swindex_class_all_to_202107.csv
rrdata/rrdatad/index/swsindex/swsindex_all_stock_class_new.xlsx
rrdata/rrdatad/industry/__init__.py
rrdata/rrdatad/instrument_code_name.py
rrdata/rrdatad/record/__init__.py
rrdata/rrdatad/record/record_data_cronly.py
rrdata/rrdatad/record/record_stock_day.py
rrdata/rrdatad/record/record_swl_data.py
rrdata/rrdatad/rrdataD_save_api.py
rrdata/rrdatad/stock/README.md
rrdata/rrdatad/stock/__init__.py
rrdata/rrdatad/stock/cons.py
rrdata/rrdatad/stock/fetch_adjfactor_tradedate.py
rrdata-0.2.1.dist-info/WHEEL
rrdata-0.2.1.dist-info/METADATA
rrdata-0.2.1.dist-info/RECORD
