Metadata-Version: 2.1
Name: rrdata
Version: 0.2.1
Summary: 
Home-page: https://github.com/romepeng/rrdata.git
Author: romepeng
Author-email: romepeng@outlook.com
Requires-Python: >=3.9,<4.0
Classifier: Programming Language :: Python :: 3
Classifier: Programming Language :: Python :: 3.10
Classifier: Programming Language :: Python :: 3.9
Project-URL: Repository, https://github.com/romepeng/rrdata.git
